latitude/__init__.py
latitude/account.py
latitude/api_keys.py
latitude/api_version.py
latitude/bandwidth.py
latitude/bandwidth_packages.py
latitude/deploy_config.py
latitude/ip_addresses.py
latitude/ipmi_credentials.py
latitude/members.py
latitude/operating_systems.py
latitude/plans.py
latitude/power_actions.py
latitude/projects.py
latitude/regions.py
latitude/rescue_mode.py
latitude/roles.py
latitude/sdk.py
latitude/server_reinstall.py
latitude/servers.py
latitude/ssh_keys.py
latitude/teams.py
latitude/user_data.py
latitude/virtual_network_assignments.py
latitude/virtual_networks.py
latitude/vpn_sessions.py
latitude/models/__init__.py
latitude/models/operations/__init__.py
latitude/models/operations/assign_server_virtual_network.py
latitude/models/operations/create_ipmi_session.py
latitude/models/operations/create_project.py
latitude/models/operations/create_server.py
latitude/models/operations/create_server_action.py
latitude/models/operations/create_server_reinstall.py
latitude/models/operations/create_virtual_network.py
latitude/models/operations/delete_api_key.py
latitude/models/operations/delete_project.py
latitude/models/operations/delete_project_ssh_key.py
latitude/models/operations/delete_project_user_data.py
latitude/models/operations/delete_virtual_networks_assignments.py
latitude/models/operations/delete_vpn_session.py
latitude/models/operations/destroy_server.py
latitude/models/operations/destroy_team_member.py
latitude/models/operations/destroy_virtual_network.py
latitude/models/operations/get_api_keys.py
latitude/models/operations/get_current_version.py
latitude/models/operations/get_ip.py
latitude/models/operations/get_ips.py
latitude/models/operations/get_plan.py
latitude/models/operations/get_plans.py
latitude/models/operations/get_plans_bandwidth.py
latitude/models/operations/get_plans_operating_system.py
latitude/models/operations/get_project.py
latitude/models/operations/get_project_ssh_key.py
latitude/models/operations/get_project_ssh_keys.py
latitude_python_sdk-2.6.6.dist-info/LICENSE
latitude_python_sdk-2.6.6.dist-info/METADATA
latitude_python_sdk-2.6.6.dist-info/WHEEL
latitude_python_sdk-2.6.6.dist-info/top_level.txt
latitude_python_sdk-2.6.6.dist-info/RECORD
